PPP_Lang_Translation/Language.py
PPP_Lang_Translation/PPP_Lang_Translation.py
PPP_Lang_Translation/__init__.py
PPP_Lang_Translation-1.0.3.dist-info/LICENSE.txt
PPP_Lang_Translation-1.0.3.dist-info/METADATA
PPP_Lang_Translation-1.0.3.dist-info/WHEEL
PPP_Lang_Translation-1.0.3.dist-info/top_level.txt
PPP_Lang_Translation-1.0.3.dist-info/RECORD
